mathjax/__init__.py
mathjax/api.py
mathjax/htdocs/config.js
mathjax/htdocs/update.js
TracMathJax-0.1.7.dist-info/METADATA
TracMathJax-0.1.7.dist-info/WHEEL
TracMathJax-0.1.7.dist-info/entry_points.txt
TracMathJax-0.1.7.dist-info/top_level.txt
TracMathJax-0.1.7.dist-info/RECORD
