Metadata-Version: 2.1
Name: TracMathJax
Version: 0.1.7
Summary: Renders mathematical equations using MathJax library.
Home-page: https://trac-hacks.org/wiki/TracMathJaxPlugin
Author: Mitar
Author-email: mitar.trac@tnode.com
License: AGPLv3
Keywords: trac plugin
Platform: UNKNOWN
Classifier: Framework :: Trac
